lemonade/__init__.py
lemonade/api.py
lemonade/backend_versions.json
lemonade/cache.py
lemonade/cli.py
lemonade/sequence.py
lemonade/state.py
lemonade/version.py
lemonade/common/__init__.py
lemonade/common/build.py
lemonade/common/cli_helpers.py
lemonade/common/exceptions.py
lemonade/common/filesystem.py
lemonade/common/inference_engines.py
lemonade/common/network.py
lemonade/common/printing.py
lemonade/common/status.py
lemonade/common/system_info.py
lemonade/common/test_helpers.py
lemonade/profilers/__init__.py
lemonade/profilers/agt_power.py
lemonade/profilers/hwinfo_power.py
lemonade/profilers/memory_tracker.py
lemonade/profilers/profiler.py
lemonade/tools/__init__.py
lemonade/tools/accuracy.py
lemonade/tools/adapter.py
lemonade/tools/bench.py
lemonade/tools/humaneval.py
lemonade/tools/management_tools.py
lemonade/tools/mmlu.py
lemonade/tools/perplexity.py
lemonade/tools/prompt.py
lemonade/tools/server_bench.py
lemonade/tools/server_load.py
lemonade/tools/tool.py
lemonade/tools/flm/__init__.py
lemonade/tools/flm/bench.py
lemonade/tools/flm/load.py
lemonade/tools/flm/utils.py
lemonade/tools/huggingface/bench.py
lemonade/tools/huggingface/load.py
lemonade/tools/huggingface/utils.py
lemonade/tools/llamacpp/bench.py
lemonade/tools/llamacpp/load.py
lemonade/tools/llamacpp/utils.py
lemonade/tools/oga/__init__.py
lemonade/tools/oga/bench.py
lemonade/tools/oga/load.py
lemonade/tools/oga/migration.py
lemonade/tools/oga/utils.py
lemonade/tools/report/__init__.py
lemonade/tools/report/llm_report.py
lemonade/tools/report/table.py
lemonade/tools/server/__init__.py
lemonade/tools/server/flm.py
lemonade/tools/server/llamacpp.py
lemonade/tools/server/serve.py
lemonade/tools/server/tool_calls.py
lemonade/tools/server/tray.py
lemonade/tools/server/webapp.py
lemonade/tools/server/wrapped_server.py
lemonade/tools/server/static/favicon.ico
lemonade/tools/server/static/index.html
lemonade/tools/server/static/logs.html
lemonade/tools/server/static/styles.css
lemonade_sdk-9.1.4.dist-info/licenses/LICENSE
lemonade_sdk-9.1.4.dist-info/licenses/NOTICE.md
lemonade_sdk-9.1.4.dist-info/METADATA
lemonade_sdk-9.1.4.dist-info/WHEEL
lemonade_sdk-9.1.4.dist-info/entry_points.txt
lemonade_sdk-9.1.4.dist-info/top_level.txt
lemonade_sdk-9.1.4.dist-info/RECORD
