Metadata-Version: 2.4
Name: lemonade-sdk
Version: 9.1.4
Summary: Lemonade SDK: Your LLM Aide for Validation and Deployment
Author-email: lemonade@amd.com
Requires-Python: >=3.10, <3.14
License-File: LICENSE
License-File: NOTICE.md
Requires-Dist: invoke>=2.0.0
Requires-Dist: onnx==1.18.0
Requires-Dist: pyyaml>=5.4
Requires-Dist: typeguard>=2.3.13
Requires-Dist: packaging>=20.9
Requires-Dist: numpy
Requires-Dist: fasteners
Requires-Dist: GitPython>=3.1.40
Requires-Dist: psutil>=6.1.1
Requires-Dist: wmi; platform_system == "Windows"
Requires-Dist: py-cpuinfo
Requires-Dist: pytz
Requires-Dist: zstandard
Requires-Dist: fastapi
Requires-Dist: uvicorn[standard]
Requires-Dist: openai<3.0.0,>=2.0.0
Requires-Dist: transformers<=4.53.2
Requires-Dist: jinja2
Requires-Dist: tabulate
Requires-Dist: sentencepiece
Requires-Dist: huggingface-hub[hf_xet]==0.33.0
Requires-Dist: python-dotenv
Requires-Dist: python-multipart
Requires-Dist: rumps>=0.4.0; sys_platform == "darwin"
Provides-Extra: oga-ryzenai
Requires-Dist: onnxruntime-genai-directml-ryzenai==0.9.2.1; extra == "oga-ryzenai"
Requires-Dist: protobuf>=6.30.1; extra == "oga-ryzenai"
Provides-Extra: oga-cpu
Requires-Dist: onnxruntime-genai==0.9.2; extra == "oga-cpu"
Requires-Dist: onnxruntime>=1.22.0; extra == "oga-cpu"
Provides-Extra: dev
Requires-Dist: torch>=2.6.0; extra == "dev"
Requires-Dist: accelerate; extra == "dev"
Requires-Dist: datasets; extra == "dev"
Requires-Dist: pandas>=1.5.3; extra == "dev"
Requires-Dist: matplotlib; extra == "dev"
Requires-Dist: human-eval-windows==1.0.4; extra == "dev"
Requires-Dist: lm-eval[api]; extra == "dev"
Provides-Extra: model-generate
Requires-Dist: model-generate==1.5.0; (platform_system == "Windows" and python_version == "3.10") and extra == "model-generate"
Dynamic: author-email
Dynamic: description
Dynamic: description-content-type
Dynamic: license-file
Dynamic: provides-extra
Dynamic: requires-dist
Dynamic: requires-python
Dynamic: summary
